fxdb.py
fxdb-0.1.0.dist-info/METADATA
fxdb-0.1.0.dist-info/WHEEL
fxdb-0.1.0.dist-info/top_level.txt
fxdb-0.1.0.dist-info/RECORD
