Metadata-Version: 2.1
Name: fxdb
Version: 0.1.0
Summary: Add your description here
Requires-Python: >=3.7
